[
	{
		"quote_id":1,
		"quote_txt":"3BB ที่สุดแห่งความเร็ว ที่สุดแห่งการบริการ"
	}
	,{
		"quote_id":2,
		"quote_txt":"3BB เน็ตบ้านเพื่อชีวิตยุคดิจิตอล"
	}
	,{
		"quote_id":3,
		"quote_txt":"3BB เชื่อมต่อคุณ เชื่อมต่อทั่วไทย สานสายใยทั่วโลก"
	}
	,{
		"quote_id":4,
		"quote_txt":"3BB Internet โครงข่ายกว้างไกล ใส่ใจในบริการ"
	}
	,{
		"quote_id":5,
		"quote_txt":"ครอบคุมทุกพื้นที่ 3BB ทั่วไทย ใส่ใจในบริการ สื่อสารเพื่ออนาคต"
	}
	,{
		"quote_id":6,
		"quote_txt":"อยู่ที่เราเลือกว่าจะจัดการเวลา หรือรอให้เวลาจัดการเรา"
	}
	,{
		"quote_id":7,
		"quote_txt":"เวลาเป็นทรัพยากรที่มีค่ามากที่สุด"
	}
	,{
		"quote_id":8,
		"quote_txt":"เรามีเวลาสำหรับสิ่งที่เราอยากทำเสมอ สิ่งที่เราขาดคือความตั้งใจ ไม่ใช่เวลา"
	}
	,{
		"quote_id":9,
		"quote_txt":"อย่าเอางานที่ทำได้วันนี้ ไปทำวันพรุ่งนี้"
	}
	,{
		"quote_id":10,
		"quote_txt":"เวลาที่หายไป คือสิ่งมีค่าที่ไม่อาจหาเจอ"
	}
	,{
		"quote_id":11,
		"quote_txt":"อย่าเสียเวลากับเวลาที่เสียไป"
	}
	,{
		"quote_id":12,
		"quote_txt":"อย่ารอโอกาสครั้งต่อไป แค่จงใช้โอกาสนี้ให้ดีที่สุด"
	}
	,{
		"quote_id":13,
		"quote_txt":"ชีวิตที่มีคุณค่า เกิดจากการใช้เวลาที่ดี"
	}
	,{
		"quote_id":14,
		"quote_txt":"3BB Fiber เน็ตบ้านแรงเต็มสปีด ราคาสุดคุ้ม"
	}
	,{
		"quote_id":15,
		"quote_txt":"3BB ที่หนึ่งของเน็ตบ้านคุณภาพ การันตีด้วยรางวัลระดับโลก"
	}
	,{
		"quote_id":16,
		"quote_txt":"3BB เน็ตบ้านมาตรฐานใหม่พร้อมความบันเทิงระดับเวิลด์คลาส"
	}
]